bluesky_browser/__init__.py
bluesky_browser/_version.py
bluesky_browser/demo.py
bluesky_browser/example_config.py
bluesky_browser/utils.py
bluesky_browser/zmq.py
bluesky_browser/artists/__init__.py
bluesky_browser/artists/mpl/__init__.py
bluesky_browser/artists/mpl/grid.py
bluesky_browser/artists/mpl/image.py
bluesky_browser/artists/mpl/line.py
bluesky_browser/frameworks/__init__.py
bluesky_browser/frameworks/qt/__init__.py
bluesky_browser/frameworks/qt/baseline.py
bluesky_browser/frameworks/qt/figures.py
bluesky_browser/frameworks/qt/header_tree.py
bluesky_browser/frameworks/qt/main.py
bluesky_browser/frameworks/qt/search.py
bluesky_browser/frameworks/qt/summary.py
bluesky_browser/frameworks/qt/utils.py
bluesky_browser/frameworks/qt/viewer.py
bluesky_browser/heuristics/__init__.py
bluesky_browser/heuristics/image.py
bluesky_browser/heuristics/line.py
bluesky_browser/heuristics/utils.py
bluesky_browser/tests/__init__.py
bluesky_browser/tests/conftest.py
bluesky_browser/tests/test_examples.py
bluesky_browser-0.1.0a7.dist-info/METADATA
bluesky_browser-0.1.0a7.dist-info/RECORD
bluesky_browser-0.1.0a7.dist-info/WHEEL
bluesky_browser-0.1.0a7.dist-info/entry_points.txt
bluesky_browser-0.1.0a7.dist-info/top_level.txt
