Metadata-Version: 2.1
Name: bluesky-browser
Version: 0.1.0a7
Summary: Library of Qt widgets for searching, viewing document streams
Home-page: https://github.com/NSLS-II/bluesky-browser
Author: Bluesky Project Contributors
Author-email: dallan@bnl.gov
License: BSD (3-clause)
Platform: UNKNOWN
Classifier: Development Status :: 2 - Pre-Alpha
Classifier: Natural Language :: English
Classifier: Programming Language :: Python :: 3
Requires-Python: >=3.6
Requires-Dist: bluesky
Requires-Dist: event-model (>=1.11.1)
Requires-Dist: databroker (>=1.0.0a1)
Requires-Dist: intake
Requires-Dist: jsonschema
Requires-Dist: matplotlib
Requires-Dist: ophyd
Requires-Dist: pyqt5 (>=5.8)
Requires-Dist: pyzmq
Requires-Dist: qtpy
Requires-Dist: suitcase-jsonl
Requires-Dist: tornado
Requires-Dist: traitlets
